mjpeg/__init__.py
mjpeg/client.py
mjpeg/server.py
py_mjpeg-1.0.1.dist-info/LICENSE
py_mjpeg-1.0.1.dist-info/METADATA
py_mjpeg-1.0.1.dist-info/WHEEL
py_mjpeg-1.0.1.dist-info/top_level.txt
py_mjpeg-1.0.1.dist-info/RECORD
