Metadata-Version: 2.1
Name: py-mjpeg
Version: 1.0.1
Summary: MJPEG Streaming Tools
Home-page: https://github.com/janakj/py-mjpeg
Author: Jan Janak
Author-email: jan@janakj.org
Classifier: Programming Language :: Python :: 3
Classifier: License :: OSI Approved :: MIT License
Classifier: Operating System :: OS Independent
Classifier: Development Status :: 5 - Production/Stable
Requires-Python: >=3
License-File: LICENSE
